privates/__about__.py
privates/__init__.py
privates/_util.py
privates/exceptions.py
privates/modifiers.py
privates_py-0.2.0.dist-info/METADATA
privates_py-0.2.0.dist-info/WHEEL
privates_py-0.2.0.dist-info/licenses/LICENSE.txt
privates_py-0.2.0.dist-info/RECORD
