Metadata-Version: 2.3
Name: privates.py
Version: 0.2.0
Summary: Stop others from touching your privates.
Project-URL: Documentation, https://privates.zintensity.dev
Project-URL: Issues, https://github.com/ZeroIntensity/privates.py/issues
Project-URL: Source, https://github.com/ZeroIntensity/privates.py
Author-email: ZeroIntensity <zintensitydev@gmail.com>
License-Expression: MIT
License-File: LICENSE.txt
Classifier: Development Status :: 4 - Beta
Classifier: Programming Language :: Python
Classifier: Programming Language :: Python :: 3.7
Classifier: Programming Language :: Python :: 3.8
Classifier: Programming Language :: Python :: 3.9
Classifier: Programming Language :: Python :: 3.10
Classifier: Programming Language :: Python :: 3.11
Classifier: Programming Language :: Python :: 3.12
Classifier: Programming Language :: Python :: Implementation :: CPython
Classifier: Programming Language :: Python :: Implementation :: PyPy
Requires-Python: >=3.8
Requires-Dist: typing-extensions
